IfxPy.cp38-win_amd64.pyd
IfxPyDbi.py
onedb-odbc-driver/bin/finderr.exe
onedb-odbc-driver/bin/iclit09b.dll
onedb-odbc-driver/bin/iclit09b.hlp
onedb-odbc-driver/bin/igl4n304.dll
onedb-odbc-driver/bin/iglxn304.dll
onedb-odbc-driver/bin/igo4n304.dll
onedb-odbc-driver/bin/irclt09b.dll
onedb-odbc-driver/bin/iregt07b.dll
onedb-odbc-driver/bin/irrgt09a.dll
onedb-odbc-driver/bin/irset09a.dll
onedb-odbc-driver/bin/onkstash.exe
onedb-odbc-driver/bin/regcopy.exe
onedb-odbc-driver/bin/setnet.exe
onedb-odbc-driver/bin/setnet.gid
onedb-odbc-driver/bin/setnet.hlp
onedb-odbc-driver/bin/sqliprt.exe
onedb-odbc-driver/etc/.isiver.1
onedb-odbc-driver/etc/.lvers_csdk
onedb-odbc-driver/etc/OneDBIndex.json
onedb-odbc-driver/etc/cmalarmprogram.bat
onedb-odbc-driver/etc/ids_master_doc.xml
onedb-odbc-driver/etc/en_us/04e4/esqlflrt.wri
onedb-odbc-driver/gls/cm3/016c.cmo
onedb-odbc-driver/gls/cm3/0333.cmo
onedb-odbc-driver/gls/cm3/0352.cmo
onedb-odbc-driver/gls/cm3/0354.cmo
onedb-odbc-driver/gls/cm3/035a.cmo
onedb-odbc-driver/gls/cm3/0362.cmo
onedb-odbc-driver/gls/cm3/0390.cmo
onedb-odbc-driver/gls/cm3/0393.cmo
onedb-odbc-driver/gls/cm3/03a4.cmo
onedb-odbc-driver/gls/cm3/03b5.cmo
onedb-odbc-driver/gls/cm3/03f3.cmo
onedb-odbc-driver/gls/cm3/03f9.cmo
onedb-odbc-driver/gls/cm3/0495.cmo
onedb-odbc-driver/gls/cm3/04e2.cmo
onedb-odbc-driver/gls/cm3/04e3.cmo
onedb-odbc-driver/gls/cm3/04e4.cmo
onedb-odbc-driver/gls/cm3/055f.cmo
onedb-odbc-driver/gls/cm3/1570.cmo
onedb-odbc-driver/gls/cm3/e005.cmo
onedb-odbc-driver/gls/cm3/e006.cmo
onedb-odbc-driver/gls/cm3/e007.cmo
onedb-odbc-driver/gls/cm3/e008.cmo
onedb-odbc-driver/gls/cm3/e009.cmo
onedb-odbc-driver/gls/cm3/e00a.cmo
onedb-odbc-driver/gls/cm3/e00c.cmo
onedb-odbc-driver/gls/cm3/e00d.cmo
onedb-odbc-driver/gls/cm3/e01c.cmo
onedb-odbc-driver/gls/cm3/e01d.cmo
onedb-odbc-driver/gls/cm3/e01f.cmo
onedb-odbc-driver/gls/cm3/e026.cmo
onedb-odbc-driver/gls/cm3/e027.cmo
onedb-odbc-driver/gls/cm3/e028.cmo
onedb-odbc-driver/gls/cm3/e02f.cmo
IfxPy-3.0.5.dist-info/LICENSE.txt
IfxPy-3.0.5.dist-info/METADATA
IfxPy-3.0.5.dist-info/WHEEL
IfxPy-3.0.5.dist-info/top_level.txt
IfxPy-3.0.5.dist-info/RECORD
