Metadata-Version: 2.1
Name: IfxPy
Version: 3.0.5
Summary: Informix native Python driver
Home-page: UNKNOWN
Author: Informix Application Development Team
License: Apache License 2.0
Project-URL: Documentation, https://github.com/OpenInformix/IfxPy/wiki
Project-URL: Funding, https://openinformix.github.io/IfxPy/
Project-URL: Say Thanks!, https://openinformix.github.io/IfxPy/
Project-URL: Source, https://github.com/OpenInformix/IfxPy
Project-URL: Tracker, https://openinformix.github.io/IfxPy/
Keywords: Informix Python Enterprise TimeSeries IoT
Platform: UNKNOWN
Classifier: Development Status :: 5 - Production/Stable
Classifier: Intended Audience :: Developers
Classifier: Topic :: Software Development
Classifier: License :: OSI Approved :: Apache Software License
Classifier: Programming Language :: Python :: 2.7
Classifier: Programming Language :: Python :: 3.4
Classifier: Programming Language :: Python :: 3.5
Classifier: Programming Language :: Python :: 3.6
Classifier: Programming Language :: Python :: 3.7
Classifier: Operating System :: Microsoft :: Windows
Classifier: Operating System :: POSIX
Classifier: Programming Language :: Python :: Implementation :: CPython
Requires-Python: ~=3.4
